Workbook

Sheet Cover
A1: ETERNAL LIMITED (NSE: ETERNAL)
A2: Equity Valuation | Discounted Cash Flow Analysis
A5: COMPANY SNAPSHOT
A6: Company | B6: Eternal Limited (formerly Zomato Limited)
A7: Ticker | B7: NSE: ETERNAL | BSE: 543320
A8: Sector | B8: Consumer Internet — Food Delivery, Quick Commerce, B2B Supplies
A9: Market Capitalisation | B9: ₹2,35,276 Cr (CMP ₹244 × 964 Cr shares, June 2025)
A10: 52-Week High / Low | B10: ₹368 / ₹213
A11: Face Value | B11: ₹1.00 per share
A12: Fiscal Year End | B12: 31 March
A13: Reporting Currency | B13: INR (all model figures in INR Crores)
A16: MODEL OVERVIEW
A17: Valuation Method | B17: Discounted Cash Flow (FCFF-based unlevered DCF)
A18: Forecast Horizon | B18: FY2026E – FY2031E (6-year explicit forecast)
A19: Terminal Value | B19: Gordon Growth Model | g = 5.5%
A20: Discount Rate | B20: WACC ≈ 14.5% (CAPM: Rf 7.0% + β 1.25 × ERP 7.0%; Kd post-tax ≈ 7.1%)
A21: Data Source | B21: Eternal Ltd Annual Report FY2024-25; BSE/NSE filings
A22: Prepared by | B22: Yogender
A23: Date | B23: June 2025
A26: DISCLAIMER: Prepared for academic and research purposes only. Does not constitute investment advice. Forward-looking projections are estimates; actual results may differ materially.

Sheet Assumptions
A1: Eternal Limited — Key Model Assumptions
A2: Blue = hardcoded input Black = formula Green = link to another sheet
A4: INR Crores, unless stated | B4: FY23A | C4: FY24A | D4: FY25A | E4: FY26E | F4: FY27E | G4: FY28E | H4: FY29E | I4: FY30E | J4: FY31E
A5: A. SEGMENT REVENUE PROJECTIONS
A6: Food Delivery | B6: 6147 | C6: 8080 | D6: 9418 | E6: =D6*1.2 -> 11301.6 | F6: =E6*1.15 -> 12996.84 | G6: =F6*1.12 -> 14556.461 | H6: =G6*1.1 -> 16012.107 | I6: =H6*1.08 -> 17293.075 | J6: =I6*1.07 -> 18503.591
A7: Quick Commerce (Blinkit) | B7: 806 | C7: 2301 | D7: 5206 | E7: =D7*1.5 -> 7809 | F7: =E7*1.4 -> 10932.6 | G7: =F7*1.3 -> 14212.38 | H7: =G7*1.2 -> 17054.856 | I7: =H7*1.15 -> 19613.084 | J7: =I7*1.12 -> 21966.655
A8: Hyperpure (B2B Supplies) | B8: 1506 | C8: 3172 | D8: 6196 | E8: =D8*1.6 -> 9913.6 | F8: =E8*1.4 -> 13879.04 | G8: =F8*1.3 -> 18042.752 | H8: =G8*1.2 -> 21651.302 | I8: =H8*1.15 -> 24898.998 | J8: =I8*1.1 -> 27388.898
A9: Going-Out & Entertainment | B9: 171 | C9: 258 | D9: 737 | E9: =D9*1.8 -> 1326.6 | F9: =E9*1.5 -> 1989.9 | G9: =F9*1.4 -> 2785.86 | H9: =G9*1.3 -> 3621.618 | I9: =H9*1.2 -> 4345.9416 | J9: =I9*1.15 -> 4997.8328
A10: Others | B10: 63 | C10: 22 | D10: 24 | E10: 30 | F10: 30 | G10: 30 | H10: 30 | I10: 30 | J10: 30
A11: Total Revenue | B11: =SUM(B6:B10) -> 8693 | C11: =SUM(C6:C10) -> 13833 | D11: =SUM(D6:D10) -> 21581 | E11: =SUM(E6:E10) -> 30380.8 | F11: =SUM(F6:F10) -> 39828.38 | G11: =SUM(G6:G10) -> 49627.453 | H11: =SUM(H6:H10) -> 58369.883 | I11: =SUM(I6:I10) -> 66181.099 | J11: =SUM(J6:J10) -> 72886.976
A12: YoY Growth | B12: — | C12: =(C11-B11)/B11 -> 0.59128034 | D12: =(D11-C11)/C11 -> 0.56010988 | E12: =(E11-D11)/D11 -> 0.40775682 | F12: =(F11-E11)/E11 -> 0.31097206 | G12: =(G11-F11)/F11 -> 0.24603242 | H12: =(H11-G11)/G11 -> 0.17616118 | I12: =(I11-H11)/H11 -> 0.13382271 | J12: =(J11-I11)/I11 -> 0.10132616
A14: B. MARGIN & PROFITABILITY ASSUMPTIONS
A15: Gross Profit Margin (%) | B15: 0.261 | C15: 0.262 | D15: 0.294 | E15: 0.32 | F15: 0.35 | G15: 0.38 | H15: 0.4 | I15: 0.42 | J15: 0.44
A16: EBITDA Margin (adj., ex-ESOP) | B16: -0.171 | C16: 0.004 | D16: 0.032 | E16: 0.05 | F16: 0.08 | G16: 0.11 | H16: 0.13 | I16: 0.15 | J16: 0.16
A17: D&A as % of Revenue | B17: 0.062 | C17: 0.043 | D17: 0.043 | E17: 0.042 | F17: 0.04 | G17: 0.038 | H17: 0.036 | I17: 0.034 | J17: 0.032
A18: Effective Tax Rate | B18: 0.04 | C18: -0.21 | D18: 0.24 | E18: 0.35 | F18: 0.35 | G18: 0.35 | H18: 0.25 | I18: 0.25 | J18: 0.25
A20: C. CAPEX, WORKING CAPITAL & OTHER
A21: Capex as % of Revenue | B21: 0.012 | C21: 0.018 | D21: 0.046 | E21: 0.055 | F21: 0.06 | G21: 0.055 | H21: 0.05 | I21: 0.045 | J21: 0.04
A22: Change in NWC as % of ΔRevenue | B22: — | C22: — | D22: — | E22: -0.03 | F22: -0.03 | G22: -0.03 | H22: -0.02 | I22: -0.02 | J22: -0.02
A23: Other Income (INR Cr) | B23: 682 | C23: 846 | D23: 1077 | E23: 1200 | F23: 1300 | G23: 1400 | H23: 1500 | I23: 1600 | J23: 1700
A24: Finance Costs (INR Cr) | B24: 49 | C24: 72 | D24: 154 | E24: 300 | F24: 350 | G24: 380 | H24: 400 | I24: 420 | J24: 440

Sheet P&L
A1: Eternal Limited — Income Statement (Consolidated)
A2: Source: Annual Report FY2024-25 | FY2026E–FY2031E: analyst estimates
A4: INR Crores, unless stated | B4: FY23A | C4: FY24A | D4: FY25A | E4: FY26E | F4: FY27E | G4: FY28E | H4: FY29E | I4: FY30E | J4: FY31E
A5: REVENUE FROM OPERATIONS
A6: Food Delivery | B6: =Assumptions!B6 -> 6147 | C6: =Assumptions!C6 -> 8080 | D6: =Assumptions!D6 -> 9418 | E6: =Assumptions!E6 -> 11301.6 | F6: =Assumptions!F6 -> 12996.84 | G6: =Assumptions!G6 -> 14556.461 | H6: =Assumptions!H6 -> 16012.107 | I6: =Assumptions!I6 -> 17293.075 | J6: =Assumptions!J6 -> 18503.591
A7: Quick Commerce (Blinkit) | B7: =Assumptions!B7 -> 806 | C7: =Assumptions!C7 -> 2301 | D7: =Assumptions!D7 -> 5206 | E7: =Assumptions!E7 -> 7809 | F7: =Assumptions!F7 -> 10932.6 | G7: =Assumptions!G7 -> 14212.38 | H7: =Assumptions!H7 -> 17054.856 | I7: =Assumptions!I7 -> 19613.084 | J7: =Assumptions!J7 -> 21966.655
A8: Hyperpure (B2B Supplies) | B8: =Assumptions!B8 -> 1506 | C8: =Assumptions!C8 -> 3172 | D8: =Assumptions!D8 -> 6196 | E8: =Assumptions!E8 -> 9913.6 | F8: =Assumptions!F8 -> 13879.04 | G8: =Assumptions!G8 -> 18042.752 | H8: =Assumptions!H8 -> 21651.302 | I8: =Assumptions!I8 -> 24898.998 | J8: =Assumptions!J8 -> 27388.898
A9: Going-Out & Entertainment | B9: =Assumptions!B9 -> 171 | C9: =Assumptions!C9 -> 258 | D9: =Assumptions!D9 -> 737 | E9: =Assumptions!E9 -> 1326.6 | F9: =Assumptions!F9 -> 1989.9 | G9: =Assumptions!G9 -> 2785.86 | H9: =Assumptions!H9 -> 3621.618 | I9: =Assumptions!I9 -> 4345.9416 | J9: =Assumptions!J9 -> 4997.8328
A10: Others | B10: =Assumptions!B10 -> 63 | C10: =Assumptions!C10 -> 22 | D10: =Assumptions!D10 -> 24 | E10: =Assumptions!E10 -> 30 | F10: =Assumptions!F10 -> 30 | G10: =Assumptions!G10 -> 30 | H10: =Assumptions!H10 -> 30 | I10: =Assumptions!I10 -> 30 | J10: =Assumptions!J10 -> 30
A11: Total Revenue | B11: =SUM(B6:B10) -> 8693 | C11: =SUM(C6:C10) -> 13833 | D11: =SUM(D6:D10) -> 21581 | E11: =SUM(E6:E10) -> 30380.8 | F11: =SUM(F6:F10) -> 39828.38 | G11: =SUM(G6:G10) -> 49627.453 | H11: =SUM(H6:H10) -> 58369.883 | I11: =SUM(I6:I10) -> 66181.099 | J11: =SUM(J6:J10) -> 72886.976
A12: YoY Growth (%) | B12: — | C12: =(C11-B11)/B11 -> 0.59128034 | D12: =(D11-C11)/C11 -> 0.56010988 | E12: =(E11-D11)/D11 -> 0.40775682 | F12: =(F11-E11)/E11 -> 0.31097206 | G12: =(G11-F11)/F11 -> 0.24603242 | H12: =(H11-G11)/G11 -> 0.17616118 | I12: =(I11-H11)/H11 -> 0.13382271 | J12: =(J11-I11)/I11 -> 0.10132616
A14: COST STRUCTURE
A15: Cost of Revenue (delivery, supply chain, COGS) | B15: =-B11*(1-Assumptions!B15) -> -6424.127 | C15: =-C11*(1-Assumptions!C15) -> -10208.754 | D15: =-D11*(1-Assumptions!D15) -> -15236.186 | E15: =-E11*(1-Assumptions!E15) -> -20658.944 | F15: =-F11*(1-Assumptions!F15) -> -25888.447 | G15: =-G11*(1-Assumptions!G15) -> -30769.021 | H15: =-H11*(1-Assumptions!H15) -> -35021.93 | I15: =-I11*(1-Assumptions!I15) -> -38385.038 | J15: =-J11*(1-Assumptions!J15) -> -40816.706
A16: Gross Profit | B16: =B11+B15 -> 2268.873 | C16: =C11+C15 -> 3624.246 | D16: =D11+D15 -> 6344.814 | E16: =E11+E15 -> 9721.856 | F16: =F11+F15 -> 13939.933 | G16: =G11+G15 -> 18858.432 | H16: =H11+H15 -> 23347.953 | I16: =I11+I15 -> 27796.062 | J16: =J11+J15 -> 32070.269
A17: Gross Margin (%) | B17: =IFERROR(B16/B11,0) -> 0.261 | C17: =IFERROR(C16/C11,0) -> 0.262 | D17: =IFERROR(D16/D11,0) -> 0.294 | E17: =IFERROR(E16/E11,0) -> 0.32 | F17: =IFERROR(F16/F11,0) -> 0.35 | G17: =IFERROR(G16/G11,0) -> 0.38 | H17: =IFERROR(H16/H11,0) -> 0.4 | I17: =IFERROR(I16/I11,0) -> 0.42 | J17: =IFERROR(J16/J11,0) -> 0.44
A19: EBITDA & OPERATING PROFIT
A20: EBITDA (adjusted, ex-ESOP) | B20: =B11*Assumptions!B16 -> -1486.503 | C20: =C11*Assumptions!C16 -> 55.332 | D20: =D11*Assumptions!D16 -> 690.592 | E20: =E11*Assumptions!E16 -> 1519.04 | F20: =F11*Assumptions!F16 -> 3186.2704 | G20: =G11*Assumptions!G16 -> 5459.0198 | H20: =H11*Assumptions!H16 -> 7588.0848 | I20: =I11*Assumptions!I16 -> 9927.1649 | J20: =J11*Assumptions!J16 -> 11661.916
A21: EBITDA Margin (%) | B21: =Assumptions!B16 -> -0.171 | C21: =Assumptions!C16 -> 0.004 | D21: =Assumptions!D16 -> 0.032 | E21: =Assumptions!E16 -> 0.05 | F21: =Assumptions!F16 -> 0.08 | G21: =Assumptions!G16 -> 0.11 | H21: =Assumptions!H16 -> 0.13 | I21: =Assumptions!I16 -> 0.15 | J21: =Assumptions!J16 -> 0.16
A22: Depreciation & Amortisation | B22: -437 | C22: -526 | D22: -863 | E22: =-E11*Assumptions!E17 -> -1275.9936 | F22: =-F11*Assumptions!F17 -> -1593.1352 | G22: =-G11*Assumptions!G17 -> -1885.8432 | H22: =-H11*Assumptions!H17 -> -2101.3158 | I22: =-I11*Assumptions!I17 -> -2250.1574 | J22: =-J11*Assumptions!J17 -> -2332.3832
A23: EBIT (Operating Profit) | B23: =B20+B22 -> -1923.503 | C23: =C20+C22 -> -470.668 | D23: =D20+D22 -> -172.408 | E23: =E20+E22 -> 243.0464 | F23: =F20+F22 -> 1593.1352 | G23: =G20+G22 -> 3573.1766 | H23: =H20+H22 -> 5486.769 | I23: =I20+I22 -> 7677.0075 | J23: =J20+J22 -> 9329.5329
A25: BELOW-THE-LINE ITEMS
A26: Other Income (treasury / interest earned) | B26: =Assumptions!B23 -> 682 | C26: =Assumptions!C23 -> 846 | D26: =Assumptions!D23 -> 1077 | E26: =Assumptions!E23 -> 1200 | F26: =Assumptions!F23 -> 1300 | G26: =Assumptions!G23 -> 1400 | H26: =Assumptions!H23 -> 1500 | I26: =Assumptions!I23 -> 1600 | J26: =Assumptions!J23 -> 1700
A27: Finance Costs | B27: =-Assumptions!B24 -> -49 | C27: =-Assumptions!C24 -> -72 | D27: =-Assumptions!D24 -> -154 | E27: =-Assumptions!E24 -> -300 | F27: =-Assumptions!F24 -> -350 | G27: =-Assumptions!G24 -> -380 | H27: =-Assumptions!H24 -> -400 | I27: =-Assumptions!I24 -> -420 | J27: =-Assumptions!J24 -> -440
A28: Profit Before Tax (PBT) | B28: =B23+B26+B27 -> -1290.503 | C28: =C23+C26+C27 -> 303.332 | D28: =D23+D26+D27 -> 750.592 | E28: =E23+E26+E27 -> 1143.0464 | F28: =F23+F26+F27 -> 2543.1352 | G28: =G23+G26+G27 -> 4593.1766 | H28: =H23+H26+H27 -> 6586.769 | I28: =I23+I26+I27 -> 8857.0075 | J28: =J23+J26+J27 -> 10589.533
A29: Income Tax Expense | B29: =-MAX(0,B28*Assumptions!B18) -> 0 | C29: =-MAX(0,C28*Assumptions!C18) -> 0 | D29: =-MAX(0,D28*Assumptions!D18) -> -180.14208 | E29: =-MAX(0,E28*Assumptions!E18) -> -400.06624 | F29: =-MAX(0,F28*Assumptions!F18) -> -890.09732 | G29: =-MAX(0,G28*Assumptions!G18) -> -1607.6118 | H29: =-MAX(0,H28*Assumptions!H18) -> -1646.6923 | I29: =-MAX(0,I28*Assumptions!I18) -> -2214.2519 | J29: =-MAX(0,J28*Assumptions!J18) -> -2647.3832
A30: Net Profit After Tax (PAT) | B30: =B28+B29 -> -1290.503 | C30: =C28+C29 -> 303.332 | D30: =D28+D29 -> 570.44992 | E30: =E28+E29 -> 742.98016 | F30: =F28+F29 -> 1653.0379 | G30: =G28+G29 -> 2985.5648 | H30: =H28+H29 -> 4940.0768 | I30: =I28+I29 -> 6642.7556 | J30: =J28+J29 -> 7942.1497
A31: PAT Margin (%) | B31: =IFERROR(B30/B11,0) -> -0.14845312 | C31: =IFERROR(C30/C11,0) -> 0.021928143 | D31: =IFERROR(D30/D11,0) -> 0.02643297 | E31: =IFERROR(E30/E11,0) -> 0.024455582 | F31: =IFERROR(F30/F11,0) -> 0.04150402 | G31: =IFERROR(G30/G11,0) -> 0.060159541 | H31: =IFERROR(H30/H11,0) -> 0.084634001 | I31: =IFERROR(I30/I11,0) -> 0.1003724 | J31: =IFERROR(J30/J11,0) -> 0.10896528

Sheet Balance Sheet
A1: Eternal Limited — Balance Sheet (Consolidated)
A2: Source: Annual Report FY2024-25 | Projections: analyst estimates
A4: INR Crores, unless stated | B4: FY23A | C4: FY24A | D4: FY25A | E4: FY26E | F4: FY27E | G4: FY28E | H4: FY29E | I4: FY30E | J4: FY31E
A5: NON-CURRENT ASSETS
A6: Net Fixed Assets (PPE + CWIP) | B6: 6351 | C6: 6466 | D6: 9683 | E6: =D6+Assumptions!E21*'P&L'!E11-(-'P&L'!E22) -> 10077.95 | F6: =E6+Assumptions!F21*'P&L'!F11-(-'P&L'!F22) -> 10874.518 | G6: =F6+Assumptions!G21*'P&L'!G11-(-'P&L'!G22) -> 11718.185 | H6: =G6+Assumptions!H21*'P&L'!H11-(-'P&L'!H22) -> 12535.363 | I6: =H6+Assumptions!I21*'P&L'!I11-(-'P&L'!I22) -> 13263.355 | J6: =I6+Assumptions!J21*'P&L'!J11-(-'P&L'!J22) -> 13846.451
A7: Non-Current Investments | B7: 6765 | C7: 11645 | D7: 13192 | E7: 14500 | F7: 15800 | G7: 17000 | H7: 18000 | I7: 19000 | J7: 20000
A8: Other Non-Current Assets | B8: 490 | C8: 1252 | D8: 3196 | E8: 3500 | F8: 3800 | G8: 4100 | H8: 4400 | I8: 4700 | J8: 5000
A9: Total Non-Current Assets | B9: =SUM(B6:B8) -> 13606 | C9: =SUM(C6:C8) -> 19363 | D9: =SUM(D6:D8) -> 26071 | E9: =SUM(E6:E8) -> 28077.95 | F9: =SUM(F6:F8) -> 30474.518 | G9: =SUM(G6:G8) -> 32818.185 | H9: =SUM(H6:H8) -> 34935.363 | I9: =SUM(I6:I8) -> 36963.355 | J9: =SUM(J6:J8) -> 38846.451
A11: CURRENT ASSETS
A12: Cash & Cash Equivalents | B12: 334 | C12: 309 | D12: 666 | E12: 1000 | F12: 1400 | G12: 2000 | H12: 2800 | I12: 3800 | J12: 5000
A13: Bank Deposits (>3 months maturity) | B13: 700 | C13: 422 | D13: 2948 | E13: 3200 | F13: 3500 | G13: 3800 | H13: 4000 | I13: 4200 | J13: 4500
A14: Current Investments (mutual funds) | B14: 1280 | C14: 1280 | D14: 2272 | E14: 2500 | F14: 2700 | G14: 2900 | H14: 3100 | I14: 3300 | J14: 3500
A15: Trade Receivables | B15: 632 | C15: 794 | D15: 1946 | E15: ='P&L'!E11/365*35 -> 2913.2274 | F15: ='P&L'!F11/365*35 -> 3819.1597 | G15: ='P&L'!G11/365*35 -> 4758.7968 | H15: ='P&L'!H11/365*35 -> 5597.1121 | I15: ='P&L'!I11/365*35 -> 6346.1328 | J15: ='P&L'!J11/365*35 -> 6989.162
A16: Inventories | B16: 300 | C16: 250 | D16: 680 | E16: ='P&L'!E11/365*20 -> 1664.7014 | F16: ='P&L'!F11/365*20 -> 2182.377 | G16: ='P&L'!G11/365*20 -> 2719.3125 | H16: ='P&L'!H11/365*20 -> 3198.3498 | I16: ='P&L'!I11/365*20 -> 3626.3616 | J16: ='P&L'!J11/365*20 -> 3993.8069
A17: Other Current Assets | B17: 3800 | C17: 2611 | D17: 8528 | E17: 9000 | F17: 9800 | G17: 10500 | H17: 11000 | I17: 11500 | J17: 12000
A18: Total Current Assets | B18: =SUM(B12:B17) -> 7046 | C18: =SUM(C12:C17) -> 5666 | D18: =SUM(D12:D17) -> 17040 | E18: =SUM(E12:E17) -> 20277.929 | F18: =SUM(F12:F17) -> 23401.537 | G18: =SUM(G12:G17) -> 26678.109 | H18: =SUM(H12:H17) -> 29695.462 | I18: =SUM(I12:I17) -> 32772.494 | J18: =SUM(J12:J17) -> 35982.969
A19: TOTAL ASSETS | B19: =B9+B18 -> 20652 | C19: =C9+C18 -> 25029 | D19: =D9+D18 -> 43111 | E19: =E9+E18 -> 48355.879 | F19: =F9+F18 -> 53876.055 | G19: =G9+G18 -> 59496.294 | H19: =H9+H18 -> 64630.825 | I19: =I9+I18 -> 69735.85 | J19: =J9+J18 -> 74829.42
A21: EQUITY & LIABILITIES
A22: Shareholders' Equity (paid-up + reserves) | B22: 19460 | C22: 20413 | D22: 30317 | E22: =D22+'P&L'!E30+800 -> 31859.98 | F22: =E22+'P&L'!F30+800 -> 34313.018 | G22: =F22+'P&L'!G30+800 -> 38098.583 | H22: =G22+'P&L'!H30+800 -> 43838.66 | I22: =H22+'P&L'!I30+800 -> 51281.415 | J22: =I22+'P&L'!J30+800 -> 60023.565
A23: Borrowings (financial debt) | B23: 507 | C23: 749 | D23: 2045 | E23: 3000 | F23: 3500 | G23: 3500 | H23: 3000 | I23: 2500 | J23: 2000
A24: Trade Payables & Other Liabilities | B24: 1632 | C24: 2194 | D24: 8374 | E24: ='P&L'!E11/365*40 -> 3329.4027 | F24: ='P&L'!F11/365*40 -> 4364.754 | G24: ='P&L'!G11/365*40 -> 5438.625 | H24: ='P&L'!H11/365*40 -> 6396.6995 | I24: ='P&L'!I11/365*40 -> 7252.7232 | J24: ='P&L'!J11/365*40 -> 7987.6138
A25: TOTAL EQUITY & LIABILITIES | B25: =SUM(B22:B24) -> 21599 | C25: =SUM(C22:C24) -> 23356 | D25: =SUM(D22:D24) -> 40736 | E25: =SUM(E22:E24) -> 38189.383 | F25: =SUM(F22:F24) -> 42177.772 | G25: =SUM(G22:G24) -> 47037.208 | H25: =SUM(H22:H24) -> 53235.359 | I25: =SUM(I22:I24) -> 61034.138 | J25: =SUM(J22:J24) -> 70011.179
A26: Balance check (assets – liabilities) | B26: =IF(ABS(B19-B25)<1,"—","CHECK") -> CHECK | C26: =IF(ABS(C19-C25)<1,"—","CHECK") -> CHECK | D26: =IF(ABS(D19-D25)<1,"—","CHECK") -> CHECK | E26: =IF(ABS(E19-E25)<1,"—","CHECK") -> CHECK | F26: =IF(ABS(F19-F25)<1,"—","CHECK") -> CHECK | G26: =IF(ABS(G19-G25)<1,"—","CHECK") -> CHECK | H26: =IF(ABS(H19-H25)<1,"—","CHECK") -> CHECK | I26: =IF(ABS(I19-I25)<1,"—","CHECK") -> CHECK | J26: =IF(ABS(J19-J25)<1,"—","CHECK") -> CHECK

Sheet Cash Flow
A1: Eternal Limited — Cash Flow Statement (Consolidated)
A2: Source: Annual Report FY2024-25 | Projections: analyst estimates
A4: INR Crores, unless stated | B4: FY23A | C4: FY24A | D4: FY25A | E4: FY26E | F4: FY27E | G4: FY28E | H4: FY29E | I4: FY30E | J4: FY31E
A5: A. OPERATING CASH FLOW
A6: EBITDA (adj., ex-ESOP) | B6: ='P&L'!B20 -> -1486.503 | C6: ='P&L'!C20 -> 55.332 | D6: ='P&L'!D20 -> 690.592 | E6: ='P&L'!E20 -> 1519.04 | F6: ='P&L'!F20 -> 3186.2704 | G6: ='P&L'!G20 -> 5459.0198 | H6: ='P&L'!H20 -> 7588.0848 | I6: ='P&L'!I20 -> 9927.1649 | J6: ='P&L'!J20 -> 11661.916
A7: (–) Cash Taxes Paid | B7: =-MAX(0,'P&L'!B28*Assumptions!B18) -> 0 | C7: =-MAX(0,'P&L'!C28*Assumptions!C18) -> 0 | D7: =-MAX(0,'P&L'!D28*Assumptions!D18) -> -180.14208 | E7: =-MAX(0,'P&L'!E28*Assumptions!E18) -> -400.06624 | F7: =-MAX(0,'P&L'!F28*Assumptions!F18) -> -890.09732 | G7: =-MAX(0,'P&L'!G28*Assumptions!G18) -> -1607.6118 | H7: =-MAX(0,'P&L'!H28*Assumptions!H18) -> -1646.6923 | I7: =-MAX(0,'P&L'!I28*Assumptions!I18) -> -2214.2519 | J7: =-MAX(0,'P&L'!J28*Assumptions!J18) -> -2647.3832
A8: (±) Change in Net Working Capital | B8: -200 | C8: 100 | D8: -150 | E8: =Assumptions!E22*('P&L'!E11-'P&L'!D11) -> -263.994 | F8: =Assumptions!F22*('P&L'!F11-'P&L'!E11) -> -283.4274 | G8: =Assumptions!G22*('P&L'!G11-'P&L'!F11) -> -293.97218 | H8: =Assumptions!H22*('P&L'!H11-'P&L'!G11) -> -174.84861 | I8: =Assumptions!I22*('P&L'!I11-'P&L'!H11) -> -156.22432 | J8: =Assumptions!J22*('P&L'!J11-'P&L'!I11) -> -134.11753
A9: Cash from Operations (CFO) | B9: -844 | C9: 646 | D9: 308 | E9: =E6+E7+E8 -> 854.97976 | F9: =F6+F7+F8 -> 2012.7457 | G9: =G6+G7+G8 -> 3557.4358 | H9: =H6+H7+H8 -> 5766.544 | I9: =I6+I7+I8 -> 7556.6887 | J9: =J6+J7+J8 -> 8880.4154
A11: B. INVESTING CASH FLOW
A12: (–) Capital Expenditure | B12: -845 | C12: -215 | D12: -936 | E12: =-Assumptions!E21*'P&L'!E11 -> -1670.944 | F12: =-Assumptions!F21*'P&L'!F11 -> -2389.7028 | G12: =-Assumptions!G21*'P&L'!G11 -> -2729.5099 | H12: =-Assumptions!H21*'P&L'!H11 -> -2918.4942 | I12: =-Assumptions!I21*'P&L'!I11 -> -2978.1495 | J12: =-Assumptions!J21*'P&L'!J11 -> -2915.479
A13: Other Investing Activities (net) | B13: 1642 | C13: -131 | D13: -7057 | E13: -500 | F13: -500 | G13: -500 | H13: -500 | I13: -500 | J13: -500
A14: Cash from Investing (CFI) | B14: 797 | C14: -348 | D14: -7993 | E14: =E12+E13 -> -2170.944 | F14: =F12+F13 -> -2889.7028 | G14: =G12+G13 -> -3229.5099 | H14: =H12+H13 -> -3418.4942 | I14: =I12+I13 -> -3478.1495 | J14: =J12+J13 -> -3415.479
A16: C. FINANCING CASH FLOW
A17: Net Borrowings (raised / repaid) | B17: 437 | C17: 202 | D17: 1296 | E17: 955 | F17: 500 | G17: 0 | H17: -500 | I17: -500 | J17: -500
A18: Equity Issuance (net) | B18: -127 | C18: -207 | D18: 8042 | E18: 0 | F18: 0 | G18: 0 | H18: 0 | I18: 0 | J18: 0
A19: Cash from Financing (CFF) | B19: -127 | C19: -207 | D19: 8042 | E19: =E17+E18 -> 955 | F19: =F17+F18 -> 500 | G19: =G17+G18 -> 0 | H19: =H17+H18 -> -500 | I19: =I17+I18 -> -500 | J19: =J17+J18 -> -500
A21: D. FREE CASH FLOW TO FIRM (FCFF) — DCF INPUT
A22: EBIT | B22: ='P&L'!B23 -> -1923.503 | C22: ='P&L'!C23 -> -470.668 | D22: ='P&L'!D23 -> -172.408 | E22: ='P&L'!E23 -> 243.0464 | F22: ='P&L'!F23 -> 1593.1352 | G22: ='P&L'!G23 -> 3573.1766 | H22: ='P&L'!H23 -> 5486.769 | I22: ='P&L'!I23 -> 7677.0075 | J22: ='P&L'!J23 -> 9329.5329
A23: (–) Taxes on EBIT [EBIT × t] | B23: =-MAX(0,'P&L'!B23*Assumptions!B18) -> 0 | C23: =-MAX(0,'P&L'!C23*Assumptions!C18) -> -98.84028 | D23: =-MAX(0,'P&L'!D23*Assumptions!D18) -> 0 | E23: =-MAX(0,'P&L'!E23*Assumptions!E18) -> -85.06624 | F23: =-MAX(0,'P&L'!F23*Assumptions!F18) -> -557.59732 | G23: =-MAX(0,'P&L'!G23*Assumptions!G18) -> -1250.6118 | H23: =-MAX(0,'P&L'!H23*Assumptions!H18) -> -1371.6923 | I23: =-MAX(0,'P&L'!I23*Assumptions!I18) -> -1919.2519 | J23: =-MAX(0,'P&L'!J23*Assumptions!J18) -> -2332.3832
A24: NOPAT (EBIT after tax) | B24: =B22+B23 -> -1923.503 | C24: =C22+C23 -> -569.50828 | D24: =D22+D23 -> -172.408 | E24: =E22+E23 -> 157.98016 | F24: =F22+F23 -> 1035.5379 | G24: =G22+G23 -> 2322.5648 | H24: =H22+H23 -> 4115.0768 | I24: =I22+I23 -> 5757.7556 | J24: =J22+J23 -> 6997.1497
A25: (+) Depreciation & Amortisation | B25: =-'P&L'!B22 -> 437 | C25: =-'P&L'!C22 -> 526 | D25: =-'P&L'!D22 -> 863 | E25: =-'P&L'!E22 -> 1275.9936 | F25: =-'P&L'!F22 -> 1593.1352 | G25: =-'P&L'!G22 -> 1885.8432 | H25: =-'P&L'!H22 -> 2101.3158 | I25: =-'P&L'!I22 -> 2250.1574 | J25: =-'P&L'!J22 -> 2332.3832
A26: (–) Capital Expenditure | B26: ='Cash Flow'!B12 -> -845 | C26: ='Cash Flow'!C12 -> -215 | D26: ='Cash Flow'!D12 -> -936 | E26: ='Cash Flow'!E12 -> -1670.944 | F26: ='Cash Flow'!F12 -> -2389.7028 | G26: ='Cash Flow'!G12 -> -2729.5099 | H26: ='Cash Flow'!H12 -> -2918.4942 | I26: ='Cash Flow'!I12 -> -2978.1495 | J26: ='Cash Flow'!J12 -> -2915.479
A27: (±) Change in NWC | B27: -200 | C27: 100 | D27: -150 | E27: ='Cash Flow'!E8 -> -263.994 | F27: ='Cash Flow'!F8 -> -283.4274 | G27: ='Cash Flow'!G8 -> -293.97218 | H27: ='Cash Flow'!H8 -> -174.84861 | I27: ='Cash Flow'!I8 -> -156.22432 | J27: ='Cash Flow'!J8 -> -134.11753
A28: Free Cash Flow to Firm (FCFF) | B28: =B24+B25+B26+B27 -> -2531.503 | C28: =C24+C25+C26+C27 -> -158.50828 | D28: =D24+D25+D26+D27 -> -395.408 | E28: =E24+E25+E26+E27 -> -500.96424 | F28: =F24+F25+F26+F27 -> -44.45712 | G28: =G24+G25+G26+G27 -> 1184.9259 | H28: =H24+H25+H26+H27 -> 3123.0498 | I28: =I24+I25+I26+I27 -> 4873.5392 | J28: =J24+J25+J26+J27 -> 6279.9363
A29: FCFF Margin (%) | B29: =IFERROR(B28/'P&L'!B11,0) -> -0.29121166 | C29: =IFERROR(C28/'P&L'!C11,0) -> -0.011458706 | D29: =IFERROR(D28/'P&L'!D11,0) -> -0.018322043 | E29: =IFERROR(E28/'P&L'!E11,0) -> -0.016489501 | F29: =IFERROR(F28/'P&L'!F11,0) -> -0.0011162171 | G29: =IFERROR(G28/'P&L'!G11,0) -> 0.02387642 | H29: =IFERROR(H28/'P&L'!H11,0) -> 0.053504472 | I29: =IFERROR(I28/'P&L'!I11,0) -> 0.073639442 | J29: =IFERROR(J28/'P&L'!J11,0) -> 0.086159925

Sheet WACC
A1: Eternal Limited — WACC — Weighted Average Cost of Capital
A2: CAPM methodology | Market-value weighted capital structure | June 2025
A4: 1. COST OF EQUITY (CAPM)
A5: Risk-Free Rate (Rf) | B5: 0.07 | C5: India 10Y G-Sec yield, Jun 2025
A6: Equity Risk Premium (ERP) | B6: 0.07 | C6: India ERP per Damodaran (Jan 2025) ~6.8%; rounded to 7.0%
A7: Beta (β) — 5Y weekly vs Nifty 50 | B7: 1.25 | C7: High-growth consumer internet platform; β > 1 appropriate
A8: Cost of Equity [Ke = Rf + β × ERP] | B8: =B5+B7*B6 -> 0.1575 | C8: Ke = Rf + Beta x ERP = 7.0% + 1.25 x 7.0% = 15.75%
A10: 2. COST OF DEBT
A11: Pre-Tax Cost of Debt (Kd, gross) | B11: 0.095 | C11: Blended: FY25 finance cost ÷ avg. borrowings; lease-inclusive
A12: Marginal Tax Rate (for interest tax shield) | B12: 0.25 | C12: Long-run normalised rate post full-profitability
A13: After-Tax Cost of Debt [Kd × (1–t)] | B13: =B11*(1-B12) -> 0.07125
A15: 3. CAPITAL STRUCTURE (MARKET-VALUE WEIGHTS)
A16: Market Cap — Equity (E) | B16: 235276 | C16: CMP ₹244 × 964 Cr shares (Jun 2025)
A17: Total Financial Debt (D) | B17: 2045 | C17: FY2025A borrowings per Balance Sheet
A18: Total Capital (V = E + D) | B18: =B16+B17 -> 237321
A19: Weight of Equity (We = E/V) | B19: =B16/B18 -> 0.99138298 | C19: Equity-dominated structure; debt < 1% of total capital
A20: Weight of Debt (Wd = D/V) | B20: =B17/B18 -> 0.0086170208
A22: 4. WACC OUTPUT
A23: WACC = We × Ke + Wd × Kd(1–t) | B23: =B19*B8+B20*B13 -> 0.15675678 | C23: Primary discount rate used in DCF
A25: 5. WACC SENSITIVITY — BETA VS EQUITY RISK PREMIUM
A26: β ↓ / ERP → | B26: 0.06 | C26: 0.065 | D26: 0.07 | E26: 0.075 | F26: 0.08
A27: 1 | B27: 0.12948888 | C27: 0.13444538 | D27: 0.13940188 | E27: 0.14435838 | F27: 0.14931488
A28: 1.1 | B28: 0.13543668 | C28: 0.14088882 | D28: 0.14634098 | E28: 0.15179313 | F28: 0.15724527
A29: 1.25 | B29: 0.14435838 | C29: 0.150554 | D29: 0.15674963 | E29: 0.16294525 | F29: 0.16914087
A30: 1.4 | B30: 0.15328007 | C30: 0.16021917 | D30: 0.16715827 | E30: 0.17409737 | F30: 0.18103648
A31: 1.5 | B31: 0.15922787 | C31: 0.16666263 | D31: 0.17409737 | E31: 0.18153212 | F31: 0.18896688

Sheet DCF
A1: Eternal Limited — DCF Valuation — FCFF-Based Unlevered DCF
A2: 6-year explicit forecast | Mid-year discounting | Gordon Growth terminal value | As of June 2025
A4: INR Crores, unless stated | B4: FY26E | C4: FY27E | D4: FY28E | E4: FY29E | F4: FY30E | G4: FY31E
A5: STEP 1 — PROJECTED FCFF (FY2026E–FY2031E)
A6: Revenue from Operations | B6: ='P&L'!E11 -> 30380.8 | C6: ='P&L'!F11 -> 39828.38 | D6: ='P&L'!G11 -> 49627.453 | E6: ='P&L'!H11 -> 58369.883 | F6: ='P&L'!I11 -> 66181.099 | G6: ='P&L'!J11 -> 72886.976
A7: Free Cash Flow to Firm (FCFF) | B7: ='Cash Flow'!E28 -> -500.96424 | C7: ='Cash Flow'!F28 -> -44.45712 | D7: ='Cash Flow'!G28 -> 1184.9259 | E7: ='Cash Flow'!H28 -> 3123.0498 | F7: ='Cash Flow'!I28 -> 4873.5392 | G7: ='Cash Flow'!J28 -> 6279.9363
A8: FCFF Margin (%) | B8: =IFERROR(B7/B6,0) -> -0.016489501 | C8: =IFERROR(C7/C6,0) -> -0.0011162171 | D8: =IFERROR(D7/D6,0) -> 0.02387642 | E8: =IFERROR(E7/E6,0) -> 0.053504472 | F8: =IFERROR(F7/F6,0) -> 0.073639442 | G8: =IFERROR(G7/G6,0) -> 0.086159925
A10: STEP 2 — DISCOUNTING TO PRESENT VALUE
A11: WACC (discount rate) | B11: =WACC!B23 -> 0.15675678 | C11: =WACC!B23 -> 0.15675678 | D11: =WACC!B23 -> 0.15675678 | E11: =WACC!B23 -> 0.15675678 | F11: =WACC!B23 -> 0.15675678 | G11: =WACC!B23 -> 0.15675678
A12: Discount Period (mid-year convention) | B12: 0.5 | C12: 1.5 | D12: 2.5 | E12: 3.5 | F12: 4.5 | G12: 5.5
A13: Discount Factor [1/(1+WACC)^t] | B13: =1/(1+B11)^B12 -> 0.92977737 | C13: =1/(1+C11)^C12 -> 0.80377949 | D13: =1/(1+D11)^D12 -> 0.69485608 | E13: =1/(1+E11)^E12 -> 0.60069333 | F13: =1/(1+F11)^F12 -> 0.51929095 | G13: =1/(1+G11)^G12 -> 0.44891974
A14: PV of FCFF | B14: =B7*B13 -> -465.78521 | C14: =C7*C13 -> -35.733721 | D14: =D7*D13 -> 823.35298 | E14: =E7*E13 -> 1875.9952 | F14: =F7*F13 -> 2530.7848 | G14: =G7*G13 -> 2819.1874
A16: STEP 3 — TERMINAL VALUE (GORDON GROWTH MODEL)
A17: Terminal Growth Rate (g) | B17: 0.055 | C17: India nominal GDP ~12%; haircut for maturity; g < WACC
A18: Terminal Year FCFF (FY2031E) | B18: ='Cash Flow'!J28 -> 6279.9363
A19: Terminal Value [TV = FCFF₂₀₃₁×(1+g) / (WACC−g)] | B19: =B18*(1+B17)/(WACC!B23-B17) -> 65109.496 | C19: Gordon Growth Model perpetuity
A20: PV of Terminal Value | B20: =B19/(1+WACC!B23)^6 -> 27176.405
A22: STEP 4 — ENTERPRISE VALUE TO EQUITY VALUE BRIDGE
A23: Sum of PV of FCFF (FY2026E–FY2031E) | B23: =SUM(B14:G14) -> 7547.8014
A24: (+) PV of Terminal Value | B24: =B20 -> 27176.405
A25: Enterprise Value (EV) | B25: =B23+B24 -> 34724.207
A26: (+) Cash & Liquid Investments (FY2025A) | B26: 5886
A27: (–) Total Financial Debt (FY2025A) | B27: -2045
A28: Equity Value | B28: =B25+B26+B27 -> 38565.207
A29: ÷ Shares Outstanding (Crores) | B29: 964
A30: Intrinsic Value per Share (₹) | B30: =B28/B29 -> 40.005401
A31: Current Market Price (CMP, ₹) | B31: 244
A32: Upside / (Downside) to CMP | B32: =(B30-B31)/B31 -> -0.83604344
A34: SANITY CHECKS
A35: Terminal Value as % of EV | B35: =B20/B25 -> 0.78263574
A36: Implied EV / FY2026E Revenue | B36: =B25/B6 -> 1.1429655
A37: Implied EV / FY2031E EBITDA | B37: =B25/'P&L'!J20 -> 2.977573
A38: Implied P/E (FY2026E) | B38: =B30/('P&L'!E30/ 964) -> 51.906106

Sheet Sensitivity
A1: Eternal Limited — Sensitivity Analysis — Intrinsic Value per Share (₹)
A2: Base: WACC 15.7%, g 5.5%, terminal EBITDA margin 16% | Base price shown in bold box | CMP ₹244
A4: TABLE 1 — Intrinsic Value per Share (₹) | WACC × Terminal Growth Rate (g)
A5: Base case: terminal EBITDA margin 16% | ★ = base scenario (WACC 15.7%)
A6: WACC ↓ / g → | B6: 0.04 | C6: 0.045 | D6: 0.05 | E6: 0.055 | F6: 0.06 | G6: 0.065 | H6: 0.07
A7: 0.12 | B7: 56 | C7: 59 | D7: 63 | E7: 67 | F7: 71 | G7: 77 | H7: 84
A8: 0.13 | B8: 49 | C8: 51 | D8: 54 | E8: 57 | F8: 60 | G8: 64 | H8: 69
A9: 0.14 | B9: 43 | C9: 45 | D9: 47 | E9: 49 | F9: 52 | G9: 55 | H9: 58
A10: 0.145 | B10: 41 | C10: 42 | D10: 44 | E10: 46 | F10: 48 | G10: 51 | H10: 53
A11: 0.15 | B11: 39 | C11: 40 | D11: 42 | E11: 43 | F11: 45 | G11: 47 | H11: 50
A12: 0.16 | B12: 35 | C12: 36 | D12: 37 | E12: 39 | F12: 40 | G12: 42 | H12: 44
A13: 0.17 | B13: 32 | C13: 33 | D13: 34 | E13: 35 | F13: 36 | G13: 37 | H13: 39
A15: TABLE 2 — Intrinsic Value per Share (₹) | WACC × Terminal EBITDA Margin (FY2031E)
A16: Terminal growth rate fixed at g = 5.5% | All other assumptions constant
A17: WACC ↓ / Margin → | B17: 0.1 | C17: 0.12 | D17: 0.14 | E17: 0.16 | F17: 0.18 | G17: 0.2 | H17: 0.22
A18: 0.12 | B18: 37 | C18: 47 | D18: 57 | E18: 67 | F18: 77 | G18: 87 | H18: 96
A19: 0.13 | B19: 32 | C19: 40 | D19: 48 | E19: 57 | F19: 65 | G19: 73 | H19: 81
A20: 0.14 | B20: 28 | C20: 35 | D20: 42 | E20: 49 | F20: 56 | G20: 63 | H20: 70
A21: 0.145 | B21: 27 | C21: 33 | D21: 40 | E21: 46 | F21: 53 | G21: 59 | H21: 65
A22: 0.15 | B22: 25 | C22: 31 | D22: 37 | E22: 43 | F22: 49 | G22: 55 | H22: 61
A23: 0.16 | B23: 23 | C23: 28 | D23: 33 | E23: 39 | F23: 44 | G23: 49 | H23: 54
A24: 0.17 | B24: 21 | C24: 26 | D24: 30 | E24: 35 | F24: 39 | G24: 44 | H24: 48
A26: Note: Bold box = base case. Values in regular weight = upside to CMP (₹244). Italics / grey = downside.
